pytest_django/__init__.py
pytest_django/compat.py
pytest_django/db_reuse.py
pytest_django/django_compat.py
pytest_django/fixtures.py
pytest_django/lazy_django.py
pytest_django/live_server_helper.py
pytest_django/migrations.py
pytest_django/plugin.py
pytest_django_ahead-3.0.0.2.dist-info/DESCRIPTION.rst
pytest_django_ahead-3.0.0.2.dist-info/METADATA
pytest_django_ahead-3.0.0.2.dist-info/RECORD
pytest_django_ahead-3.0.0.2.dist-info/WHEEL
pytest_django_ahead-3.0.0.2.dist-info/entry_points.txt
pytest_django_ahead-3.0.0.2.dist-info/metadata.json
pytest_django_ahead-3.0.0.2.dist-info/top_level.txt
